mkdocs_add_teaser_plugin/__init__.py
mkdocs_add_teaser_plugin/plugin.py
mkdocs_add_teaser-0.9.1.dist-info/LICENSE
mkdocs_add_teaser-0.9.1.dist-info/METADATA
mkdocs_add_teaser-0.9.1.dist-info/WHEEL
mkdocs_add_teaser-0.9.1.dist-info/entry_points.txt
mkdocs_add_teaser-0.9.1.dist-info/top_level.txt
mkdocs_add_teaser-0.9.1.dist-info/RECORD
